MANIFEST.in
setup.cfg
setup.py
android_benchmark_views.egg-info/PKG-INFO
android_benchmark_views.egg-info/SOURCES.txt
android_benchmark_views.egg-info/dependency_links.txt
android_benchmark_views.egg-info/entry_points.txt
android_benchmark_views.egg-info/not-zip-safe
android_benchmark_views.egg-info/requires.txt
android_benchmark_views.egg-info/top_level.txt
android_benchmark_views_app/__init__.py
android_benchmark_views_app/admin.py
android_benchmark_views_app/extension.py
android_benchmark_views_app/helpers.py
android_benchmark_views_app/models.py
android_benchmark_views_app/urls.py
android_benchmark_views_app/views.py
android_benchmark_views_app/migrations/0001_initial.py
android_benchmark_views_app/migrations/0002_auto__add_field_benchmarkreport_can_publish__chg_field_benchmarkreport.py
android_benchmark_views_app/migrations/__init__.py
android_benchmark_views_app/static/android_benchmark_views_app/css/bmarks.css
android_benchmark_views_app/static/android_benchmark_views_app/js/jquery.flot.errorbars.js
android_benchmark_views_app/static/android_benchmark_views_app/js/jquery.flot.js
android_benchmark_views_app/static/android_benchmark_views_app/js/jquery.flot.navigate.js
android_benchmark_views_app/templates/android_benchmark_views_app/index.html
android_benchmark_views_app/templates/android_benchmark_views_app/report.html
android_benchmark_views_app/templates/android_benchmark_views_app/run.html