Metadata-Version: 1.0
Name: android-benchmark-views
Version: 0.1.7
Summary: LAVA Android Benchmark Views Application
Home-page: UNKNOWN
Author: Andy Doan
Author-email: andy.doan@linaro.org
License: AGPL
Platform: UNKNOWN
